neo4j_graphrag/__init__.py
neo4j_graphrag/embeddings/__init__.py
neo4j_graphrag/embeddings/base.py
neo4j_graphrag/embeddings/cohere.py
neo4j_graphrag/embeddings/mistral.py
neo4j_graphrag/embeddings/ollama.py
neo4j_graphrag/embeddings/openai.py
neo4j_graphrag/embeddings/sentence_transformers.py
neo4j_graphrag/embeddings/vertexai.py
neo4j_graphrag/exceptions.py
neo4j_graphrag/experimental/__init__.py
neo4j_graphrag/experimental/components/__init__.py
neo4j_graphrag/experimental/components/embedder.py
neo4j_graphrag/experimental/components/entity_relation_extractor.py
neo4j_graphrag/experimental/components/kg_writer.py
neo4j_graphrag/experimental/components/lexical_graph.py
neo4j_graphrag/experimental/components/neo4j_reader.py
neo4j_graphrag/experimental/components/pdf_loader.py
neo4j_graphrag/experimental/components/resolver.py
neo4j_graphrag/experimental/components/schema.py
neo4j_graphrag/experimental/components/text_splitters/__init__.py
neo4j_graphrag/experimental/components/text_splitters/base.py
neo4j_graphrag/experimental/components/text_splitters/fixed_size_splitter.py
neo4j_graphrag/experimental/components/text_splitters/langchain.py
neo4j_graphrag/experimental/components/text_splitters/llamaindex.py
neo4j_graphrag/experimental/components/types.py
neo4j_graphrag/experimental/pipeline/__init__.py
neo4j_graphrag/experimental/pipeline/component.py
neo4j_graphrag/experimental/pipeline/config/__init__.py
neo4j_graphrag/experimental/pipeline/config/base.py
neo4j_graphrag/experimental/pipeline/config/config_reader.py
neo4j_graphrag/experimental/pipeline/config/object_config.py
neo4j_graphrag/experimental/pipeline/config/param_resolver.py
neo4j_graphrag/experimental/pipeline/config/pipeline_config.py
neo4j_graphrag/experimental/pipeline/config/runner.py
neo4j_graphrag/experimental/pipeline/config/template_pipeline/__init__.py
neo4j_graphrag/experimental/pipeline/config/template_pipeline/base.py
neo4j_graphrag-1.6.0.dist-info/LICENSE.APACHE2.txt
neo4j_graphrag-1.6.0.dist-info/LICENSE.PYTHON.txt
neo4j_graphrag-1.6.0.dist-info/LICENSE.txt
neo4j_graphrag-1.6.0.dist-info/METADATA
neo4j_graphrag-1.6.0.dist-info/NOTICE.txt
neo4j_graphrag-1.6.0.dist-info/WHEEL
neo4j_graphrag-1.6.0.dist-info/RECORD
