Metadata-Version: 2.3
Name: neo4j-graphrag
Version: 1.6.0
Summary: Python package to allow easy integration to Neo4j's GraphRAG features
License: Apache License, Version 2.0
Author: Neo4j, Inc
Author-email: team-gen-ai@neo4j.com
Requires-Python: >=3.9.0,<4.0.0
Classifier: License :: Other/Proprietary License
Classifier: Programming Language :: Python :: 3
Classifier: Programming Language :: Python :: 3.9
Classifier: Programming Language :: Python :: 3.10
Classifier: Programming Language :: Python :: 3.11
Classifier: Programming Language :: Python :: 3.12
Classifier: Programming Language :: Python :: 3.13
Provides-Extra: anthropic
Provides-Extra: cohere
Provides-Extra: examples
Provides-Extra: experimental
Provides-Extra: google
Provides-Extra: kg-creation-tools
Provides-Extra: mistralai
Provides-Extra: ollama
Provides-Extra: openai
Provides-Extra: pinecone
Provides-Extra: qdrant
Provides-Extra: sentence-transformers
Provides-Extra: weaviate
Requires-Dist: anthropic (>=0.49.0,<0.50.0) ; extra == "anthropic"
Requires-Dist: cohere (>=5.9.0,<6.0.0) ; extra == "cohere"
Requires-Dist: fsspec (>=2024.9.0,<2025.0.0)
Requires-Dist: google-cloud-aiplatform (>=1.66.0,<2.0.0) ; extra == "google"
Requires-Dist: json-repair (>=0.39.1,<0.40.0)
Requires-Dist: langchain-text-splitters (>=0.3.0,<0.4.0) ; extra == "experimental"
Requires-Dist: llama-index (>=0.12.0,<0.13.0) ; extra == "experimental"
Requires-Dist: mistralai (>=1.0.3,<2.0.0) ; extra == "mistralai"
Requires-Dist: neo4j (>=5.17.0,<6.0.0)
Requires-Dist: ollama (>=0.4.4,<0.5.0) ; extra == "ollama"
Requires-Dist: openai (>=1.51.1,<2.0.0) ; extra == "openai"
Requires-Dist: pinecone-client (>=4.1.0,<5.0.0) ; extra == "pinecone"
Requires-Dist: pydantic (>=2.6.3,<3.0.0)
Requires-Dist: pygraphviz (>=1.0.0,<2.0.0) ; (python_version < "3.10") and (extra == "kg-creation-tools" or extra == "experimental")
Requires-Dist: pygraphviz (>=1.13.0,<2.0.0) ; (python_version >= "3.10" and python_full_version < "4.0.0") and (extra == "kg-creation-tools" or extra == "experimental")
Requires-Dist: pypdf (>=5.1.0,<6.0.0)
Requires-Dist: pyyaml (>=6.0.2,<7.0.0)
Requires-Dist: qdrant-client (>=1.11.3,<2.0.0) ; extra == "qdrant"
Requires-Dist: sentence-transformers (>=3.0.0,<4.0.0) ; extra == "sentence-transformers"
Requires-Dist: types-pyyaml (>=6.0.12.20240917,<7.0.0.0)
Requires-Dist: weaviate-client (>=4.6.1,<5.0.0) ; extra == "weaviate"
Project-URL: Homepage, https://neo4j.com/
Project-URL: Repository, https://github.com/neo4j/neo4j-graphrag-python
